krembil_kit/__init__.py
krembil_kit/connectivity_analyzer.py
krembil_kit/connectivity_reader.py
krembil_kit/edf_loader.py
krembil_kit/good_bad_classes.npy
krembil_kit/logreg_good_bad.pkl
krembil_kit/spectral_analyzer.py
krembil_kit/trigger_detector.py
krembil_kit-1.0.7.dist-info/licenses/LICENSE
krembil_kit-1.0.7.dist-info/METADATA
krembil_kit-1.0.7.dist-info/WHEEL
krembil_kit-1.0.7.dist-info/top_level.txt
krembil_kit-1.0.7.dist-info/RECORD
